{
    "@context": "dtmi:dtdl:context;2",
    "@type": "Interface",
    "@id": "dtmi:iec_ch:TC57:2013:CIM_schema_cim16:AccumulatorLimitSet;1",
    "displayName": "AccumulatorLimitSet",
    "description": "An AccumulatorLimitSet specifies a set of Limits that are associated with an Accumulator measurement.",
    "extends": [
        "dtmi:iec_ch:TC57:2013:CIM_schema_cim16:LimitSet;1"
    ],
    "contents": [
        {
            "@type": "Relationship",
            "name": "Measurements",
            "displayName": "AccumulatorLimitSet.Measurements",
            "description": "A measurement may have zero or more limit ranges defined for it.",
            "target": "dtmi:iec_ch:TC57:2013:CIM_schema_cim16:Accumulator;1"
        }
    ]
}