{
    "@context": "dtmi:dtdl:context;2",
    "@type": "Interface",
    "@id": "dtmi:iec:cim:schema:DCGround;16",
    "displayName": "DCGround",
    "description": "A ground within a DC system.",
    "comment": "concrete",
    "extends": [
        "dtmi:iec:cim:schema:DCConductingEquipment;16"
    ],
    "contents": [
        {
            "@id": "dtmi:iec:cim:schema:DCGround:inductance;16",
            "@type": "Property",
            "name": "DCGround_inductance",
            "displayName": "DCGround.inductance",
            "description": "Inductance to ground.",
            "schema": "float"
        },
        {
            "@id": "dtmi:iec:cim:schema:DCGround:r;16",
            "@type": "Property",
            "name": "DCGround_r",
            "displayName": "DCGround.r",
            "description": "Resistance to ground.",
            "schema": "float"
        }
    ]
}