{
    "@context": "dtmi:dtdl:context;2",
    "@type": "Interface",
    "@id": "dtmi:iec_ch:TC57:2013:CIM_schema_cim16:DiagramObjectStyle;1",
    "displayName": "DiagramObjectStyle",
    "description": "A reference to a style used by the originating system for a diagram object.  A diagram object style describes information such as line thickness, shape such as circle or rectangle etc, and color.",
    "extends": [
        "dtmi:iec_ch:TC57:2013:CIM_schema_cim16:IdentifiedObject;1"
    ],
    "contents": []
}